LICENSE
MANIFEST.in
README.rst
setup.cfg
setup.py
stick_protocol/__init__.py
stick_protocol/apps.py
stick_protocol/models.py
stick_protocol/stick_protocol.py
stick_protocol/migrations/0001_initial.py
stick_protocol/migrations/0001_migrations.py
stick_protocol/migrations/0002_auto_20210604_1545.py
stick_protocol/migrations/0003_party_timestamp.py
stick_protocol/migrations/0004_auto_20210625_1528.py
stick_protocol/migrations/0005_party_timestamp.py
stick_protocol/migrations/0006_auto_20210625_1532.py
stick_protocol/migrations/0007_auto_20210625_1554.py
stick_protocol/migrations/0008_auto_20210630_1314.py
stick_protocol/migrations/0009_auto_20210703_1413.py
stick_protocol/migrations/0010_auto_20210711_1851.py
stick_protocol/migrations/0011_auto_20210717_1937.py
stick_protocol/migrations/0012_auto_20220917_1802.py
stick_protocol/migrations/0013_auto_20220917_1815.py
stick_protocol/migrations/__init__.py
stick_protocol_server.egg-info/PKG-INFO
stick_protocol_server.egg-info/SOURCES.txt
stick_protocol_server.egg-info/dependency_links.txt
stick_protocol_server.egg-info/top_level.txt